airflow_ray_executor/__init__.py
airflow_ray_executor/ray_executor.py
airflow_ray_executor/tests/__init__.py
airflow_ray_executor/tests/conftest.py
airflow_ray_executor/tests/test_ray_executor.py
airflow_ray_executor-0.0.1.dist-info/LICENSE
airflow_ray_executor-0.0.1.dist-info/METADATA
airflow_ray_executor-0.0.1.dist-info/WHEEL
airflow_ray_executor-0.0.1.dist-info/entry_points.txt
airflow_ray_executor-0.0.1.dist-info/top_level.txt
airflow_ray_executor-0.0.1.dist-info/RECORD
