Metadata-Version: 2.1
Name: airflow-ray-executor
Version: 0.0.1
Summary: Airflow executor implemented using ray
Home-page: https://github.com/staneyffer/airflow-ray-executor
Author: staneyffer
Author-email: staneyffer@gmail.com
License: Apache License 2.0
Platform: UNKNOWN
Classifier: Topic :: Software Development :: Libraries :: Python Modules
Classifier: Operating System :: OS Independent
Classifier: Programming Language :: Python
Classifier: Programming Language :: Python :: 3.6
Classifier: Programming Language :: Python :: 3.7
Classifier: Programming Language :: Python :: 3.8
Requires-Python: ~=3.7
License-File: LICENSE
Requires-Dist: ray
